[
  {
		"title" : "加入豹豹神教",
		"artist" : "來豹豹",
		"url" : "https://i.imgur.com/dD7Jisn.jpg",
		"image" : "https://i.imgur.com/1WL7sx4.jpg"

  },
 {
		"title" : "皮卡吃鋼蕉",
		"artist" : "來豹豹",
		"url" : "https://i.imgur.com/niUaAVw.jpg",
		"image" : "https://i.imgur.com/Xy3MVFk.jpg"

  },
  {
		"title" : "飆車仔孔明",
		"artist" : "睡屁阿!起來嗨",
		"url" : "https://i.imgur.com/gdxdYZW.jpg",
		"image" : "https://i.imgur.com/cd1wtds.jpg"

  },
  {
		"title" : "鬼鬼吃冰冰",
		"artist" : "阿~好色阿",
		"url" : "https://i.imgur.com/9JQ3I6x.jpg",
		"image" : "https://i.imgur.com/F2N6Uxo.jpg"

  },
  {
		"title" : "貓哈欠",
		"artist" : "喵喵~~~~~我舔不到屁股嗚嗚!",
		"url" : "https://i.imgur.com/LIYIi2o.jpg",
		"image" : "https://i.imgur.com/KDPyoPv.jpg"

  }
]